halerium/__init__.py
halerium/version.py
halerium/causal_structure/__init__.py
halerium/core/__init__.py
halerium/core/_analytics/__init__.py
halerium/core/_analytics/events.py
halerium/core/_analytics/runtime_id.py
halerium/core/_configuration/__init__.py
halerium/core/_configuration/config_initialization.py
halerium/core/_configuration/config_specification.py
halerium/core/_configuration/config_specification_functions.py
halerium/core/_licensing/__init__.py
halerium/core/_licensing/halerium_license.py
halerium/core/_licensing/license_manager.py
halerium/core/_licensing/license_metaclass.py
halerium/core/causal_calculus/__init__.py
halerium/core/causal_calculus/do.py
halerium/core/causal_structure/__init__.py
halerium/core/causal_structure/causal_structure.py
halerium/core/causal_structure/dependencies.py
halerium/core/compiler/__init__.py
halerium/core/compiler/compiler_base.py
halerium/core/compiler/compiler_tensor_flow.py
halerium/core/compiler/tensor_board_mockup.py
halerium/core/data_linker/__init__.py
halerium/core/data_linker/data_linker.py
halerium/core/data_linker/get_data_linker.py
halerium/core/distribution/__init__.py
halerium/core/distribution/adapt_distribution.py
halerium/core/distribution/bernoulli_distribution.py
halerium/core/distribution/categorical_distribution.py
halerium/core/distribution/dirac_distribution.py
halerium/core/distribution/distribution_base.py
halerium/core/distribution/distribution_name.py
halerium/core/distribution/exponential_distribution.py
halerium/core/distribution/laplace_distribution.py
halerium/core/distribution/log_normal_distribution.py
halerium/core/distribution/no_distribution.py
halerium/core/distribution/normal_distribution.py
halerium/core/distribution/poisson_distribution.py
halerium/core/distribution/uniform_distribution.py
halerium/core/entity/__init__.py
halerium/core/entity/entity.py
halerium/core/graph/__init__.py
halerium/core/graph/graph.py
halerium/core/graph/inputs.py
halerium/core/graph/link.py
halerium-3.3.1.dist-info/METADATA
halerium-3.3.1.dist-info/WHEEL
halerium-3.3.1.dist-info/entry_points.txt
halerium-3.3.1.dist-info/top_level.txt
halerium-3.3.1.dist-info/RECORD
