Metadata-Version: 2.1
Name: halerium
Version: 3.3.1
Summary: Halerium is a Python package for building, training and evaluating Bayesian statistical models for the purposes of machine learning, parameter inference and causal inference.
Home-page: https://erium.de
Author: Erium GmbH
Author-email: info@erium.de
License: https://erium.de/halerium-eula.txt
Project-URL: Documentation, https://hal.erium.io
Platform: UNKNOWN
Requires-Dist: tensorflow (<2.9,>=2.3)
Requires-Dist: pandas
Requires-Dist: numpy
Requires-Dist: scipy
Requires-Dist: requests
Requires-Dist: packaging
Requires-Dist: ipython
Requires-Dist: rsa
